[
  {
    "id": "m_001",
    "name": "フレイムパピー",
    "main_element": "fire",
    "sub_element": "none",
    "base_stats": {
      "hp": 200, "atk": 40, "def": 30, "mag": 20, "spd": 25, "max_st": 80, "st_rec": 5
    },
    "params": {
      "size": 60, "hardness": 50, "intelligence": 40
    },
    "skills": ["strike", "fireball"]
  },
  {
    "id": "m_002",
    "name": "アクアタートル",
    "main_element": "water",
    "sub_element": "earth",
    "base_stats": {
      "hp": 250, "atk": 25, "def": 50, "mag": 15, "spd": 10, "max_st": 120, "st_rec": 5
    },
    "params": {
      "size": 50, "hardness": 70, "intelligence": 30
    },
    "skills": ["strike", "water_gun", "heal_st"]
  },
  {
    "id": "m_003",
    "name": "サンダーバード",
    "main_element": "thunder",
    "sub_element": "wind",
    "base_stats": {
      "hp": 150, "atk": 30, "def": 20, "mag": 45, "spd": 40, "max_st": 70, "st_rec": 15
    },
    "params": {
      "size": 40, "hardness": 40, "intelligence": 70
    },
    "skills": ["strike", "smash"]
  },
  {
    "id": "m_004",
    "name": "ゴーレム",
    "main_element": "earth",
    "sub_element": "none",
    "base_stats": {
      "hp": 300, "atk": 50, "def": 60, "mag": 5, "spd": 5, "max_st": 150, "st_rec": 0
    },
    "params": {
      "size": 60, "hardness": 80, "intelligence": 10
    },
    "skills": ["smash"]
  },
  {
    "id": "m_005",
    "name": "シャドウアサシン",
    "main_element": "dark",
    "sub_element": "none",
    "base_stats": {
      "hp": 120, "atk": 60, "def": 15, "mag": 10, "spd": 50, "max_st": 50, "st_rec": 10
    },
    "params": {
      "size": 40, "hardness": 30, "intelligence": 80
    },
    "skills": ["strike", "pierce_needle"]
  },
  {
    "id": "m_006",
    "name": "ホーリーナイト",
    "main_element": "light",
    "sub_element": "fire",
    "base_stats": {
      "hp": 220, "atk": 35, "def": 40, "mag": 30, "spd": 20, "max_st": 100, "st_rec": 10
    },
    "params": {
      "size": 50, "hardness": 50, "intelligence": 50
    },
    "skills": ["strike", "heal_st"]
  }
]
